strongmock/__init__.py
strongmock-0.1.0.dist-info/LICENSE
strongmock-0.1.0.dist-info/METADATA
strongmock-0.1.0.dist-info/WHEEL
strongmock-0.1.0.dist-info/top_level.txt
strongmock-0.1.0.dist-info/RECORD
