Metadata-Version: 2.1
Name: strongmock
Version: 0.1.0
Summary: StrongMock is a powerful mocking library for Python that leverages low-level ctypes functionality to provide extensive mocking capabilities. Some care may be needed while using this.
Author-email: Arrman Anicket Saha <arrmansa99+430@gmail.com>
Project-URL: Homepage, https://github.com/arrmansa/strongmock
Project-URL: Bug Tracker, https://github.com/arrmansa/strongmock/issues
Classifier: Programming Language :: Python :: 3
Classifier: License :: OSI Approved :: The Unlicense (Unlicense)
Classifier: Operating System :: OS Independent
Requires-Python: >=3.7
License-File: LICENSE
